rslsync/__init__.py
rslsync/api.py
rslsync/cli.py
rslsync/commands/__init__.py
rslsync/commands/file.py
rslsync/commands/folder.py
rslsync/commands/fs.py
rslsync/commands/general.py
rslsync/commands/stat.py
rslsync-0.4.1.dist-info/LICENSE
rslsync-0.4.1.dist-info/WHEEL
rslsync-0.4.1.dist-info/entry_points.txt
rslsync-0.4.1.dist-info/METADATA
rslsync-0.4.1.dist-info/RECORD
