Metadata-Version: 2.1
Name: rslsync
Version: 0.4.1
Summary: A Python client library and CLI of unofficial Resilio Sync API
Home-page: https://github.com/zhongkechen/python-resilio-sync-unofficial
License: MIT
Keywords: resilio,btsync,sync,unofficial
Author: Zhongke Chen
Author-email: github@ch3n2k.com
Requires-Python: >=3.7,<4.0
Classifier: Development Status :: 3 - Alpha
Classifier: License :: OSI Approved :: MIT License
Classifier: Programming Language :: Python :: 3
Classifier: Programming Language :: Python :: 3.7
Classifier: Programming Language :: Python :: 3.8
Classifier: Programming Language :: Python :: 3.9
Classifier: Programming Language :: Python :: 3.10
Classifier: Programming Language :: Python :: 3.11
Classifier: Topic :: Communications :: File Sharing
Project-URL: Documentation, https://github.com/zhongkechen/python-resilio-sync-unofficial
Project-URL: Repository, https://github.com/zhongkechen/python-resilio-sync-unofficial
